adr_kit/__init__.py
adr_kit/cli.py
adr_kit/context/__init__.py
adr_kit/context/analyzer.py
adr_kit/context/guidance.py
adr_kit/context/models.py
adr_kit/context/planner.py
adr_kit/context/ranker.py
adr_kit/contract/__init__.py
adr_kit/contract/builder.py
adr_kit/contract/cache.py
adr_kit/contract/merger.py
adr_kit/contract/models.py
adr_kit/core/__init__.py
adr_kit/core/immutability.py
adr_kit/core/model.py
adr_kit/core/parse.py
adr_kit/core/policy_extractor.py
adr_kit/core/validate.py
adr_kit/enforce/__init__.py
adr_kit/enforce/eslint.py
adr_kit/enforce/ruff.py
adr_kit/gate/__init__.py
adr_kit/gate/models.py
adr_kit/gate/policy_engine.py
adr_kit/gate/policy_gate.py
adr_kit/gate/technical_choice.py
adr_kit/guard/__init__.py
adr_kit/guard/detector.py
adr_kit/guardrail/__init__.py
adr_kit/guardrail/config_writer.py
adr_kit/guardrail/file_monitor.py
adr_kit/guardrail/manager.py
adr_kit/guardrail/models.py
adr_kit/index/__init__.py
adr_kit/index/json_index.py
adr_kit/index/sqlite_index.py
adr_kit/mcp/__init__.py
adr_kit/mcp/models.py
adr_kit/mcp/server.py
adr_kit/semantic/__init__.py
adr_kit/semantic/retriever.py
adr_kit/workflows/__init__.py
adr_kit/workflows/analyze.py
adr_kit/workflows/approval.py
adr_kit/workflows/base.py
adr_kit/workflows/creation.py
adr_kit/workflows/planning.py
adr_kit/workflows/preflight.py
adr_kit/workflows/supersede.py
adr_kit-0.2.5.dist-info/licenses/LICENSE
adr_kit-0.2.5.dist-info/METADATA
adr_kit-0.2.5.dist-info/WHEEL
adr_kit-0.2.5.dist-info/entry_points.txt
adr_kit-0.2.5.dist-info/top_level.txt
adr_kit-0.2.5.dist-info/RECORD
