Metadata-Version: 2.4
Name: adr-kit
Version: 0.2.5
Summary: A toolkit for managing Architectural Decision Records (ADRs) in MADR format
Author: ADR Kit Contributors
License-Expression: MIT
Project-URL: Homepage, https://github.com/your-org/adr-kit
Project-URL: Repository, https://github.com/your-org/adr-kit
Classifier: Development Status :: 3 - Alpha
Classifier: Intended Audience :: Developers
Classifier: Programming Language :: Python :: 3
Classifier: Programming Language :: Python :: 3.10
Classifier: Programming Language :: Python :: 3.11
Classifier: Programming Language :: Python :: 3.12
Requires-Python: >=3.10
License-File: LICENSE
Requires-Dist: pydantic>=2.0.0
Requires-Dist: pydantic[email]>=2.0.0
Requires-Dist: typer>=0.9.0
Requires-Dist: rich>=13.0.0
Requires-Dist: pyyaml>=6.0
Requires-Dist: jsonschema>=4.17.0
Requires-Dist: pathspec>=0.11.0
Requires-Dist: sentence-transformers>=2.0.0
Requires-Dist: faiss-cpu>=1.7.0
Requires-Dist: numpy>=1.21.0
Requires-Dist: fastmcp>=0.1.0
Requires-Dist: jsonlines>=4.0.0
Requires-Dist: toml>=0.10.2
Requires-Dist: requests>=2.25.0
Provides-Extra: dev
Requires-Dist: pytest>=7.0.0; extra == "dev"
Requires-Dist: pytest-cov>=4.0.0; extra == "dev"
Requires-Dist: black>=23.0.0; extra == "dev"
Requires-Dist: ruff>=0.1.0; extra == "dev"
Requires-Dist: mypy>=1.0.0; extra == "dev"
Requires-Dist: psutil>=5.9.0; extra == "dev"
Requires-Dist: types-PyYAML>=6.0.0; extra == "dev"
Requires-Dist: types-toml>=0.10.0; extra == "dev"
Requires-Dist: types-jsonschema>=4.17.0; extra == "dev"
Requires-Dist: types-requests>=2.25.0; extra == "dev"
Dynamic: license-file
